[
  {
    "model": "verbs.tenses",
    "pk": 1,
    "fields": {
      "rank": 1,
      "tense": {
        "major": "1",
        "minor": "1"
      }
    }
  },
  {
    "model": "verbs.tenses",
    "pk": 2,
    "fields": {
      "rank": 2,
      "tense": {
        "major": "1",
        "minor": "2"
      }
    }
  },
  {
    "model": "verbs.tenses",
    "pk": 3,
    "fields": {
      "rank": 3,
      "tense": {
        "major": "1",
        "minor": "3"
      }
    }
  },
  {
    "model": "verbs.tenses",
    "pk": 4,
    "fields": {
      "rank": 4,
      "tense": {
        "major": "1",
        "minor": "4"
      }
    }
  },
  {
    "model": "verbs.tenses",
    "pk": 5,
    "fields": {
      "rank": 5,
      "tense": {
        "major": "1",
        "minor": "5"
      }
    }
  },
  {
    "model": "verbs.tenses",
    "pk": 6,
    "fields": {
      "rank": 6,
      "tense": {
        "major": "1",
        "minor": "6"
      }
    }
  },
  {
    "model": "verbs.tenses",
    "pk": 7,
    "fields": {
      "rank": 7,
      "tense": {
        "major": "1",
        "minor": "7"
      }
    }
  },
  {
    "model": "verbs.tenses",
    "pk": 8,
    "fields": {
      "rank": 8,
      "tense": {
        "major": "1",
        "minor": "8"
      }
    }
  },
  {
    "model": "verbs.tenses",
    "pk": 9,
    "fields": {
      "rank": 9,
      "tense": {
        "major": "1",
        "minor": "9"
      }
    }
  },
  {
    "model": "verbs.tenses",
    "pk": 10,
    "fields": {
      "rank": 10,
      "tense": {
        "major": "1",
        "minor": "10"
      }
    }
  },
  {
    "model": "verbs.tenses",
    "pk": 11,
    "fields": {
      "rank": 11,
      "tense": {
        "major": "2",
        "minor": "11"
      }
    }
  },
  {
    "model": "verbs.tenses",
    "pk": 12,
    "fields": {
      "rank": 12,
      "tense": {
        "major": "3",
        "minor": "1"
      }
    }
  },
  {
    "model": "verbs.tenses",
    "pk": 13,
    "fields": {
      "rank": 13,
      "tense": {
        "major": "3",
        "minor": "2"
      }
    }
  },
  {
    "model": "verbs.tenses",
    "pk": 14,
    "fields": {
      "rank": 14,
      "tense": {
        "major": "3",
        "minor": "3"
      }
    }
  },
  {
    "model": "verbs.tenses",
    "pk": 15,
    "fields": {
      "rank": 15,
      "tense": {
        "major": "3",
        "minor": "5"
      }
    }
  },
  {
    "model": "verbs.tenses",
    "pk": 16,
    "fields": {
      "rank": 16,
      "tense": {
        "major": "3",
        "minor": "7"
      }
    }
  },
  {
    "model": "verbs.tenses",
    "pk": 17,
    "fields": {
      "rank": 17,
      "tense": {
        "major": "3",
        "minor": "12"
      }
    }
  },
  {
    "model": "verbs.tenses",
    "pk": 18,
    "fields": {
      "rank": 18,
      "tense": {
        "major": "3",
        "minor": "13"
      }
    }
  },
  {
    "model": "verbs.tenses",
    "pk": 19,
    "fields": {
      "rank": 19,
      "tense": {
        "major": "3",
        "minor": "14"
      }
    }
  },
  {
    "model": "verbs.tenses",
    "pk": 20,
    "fields": {
      "rank": 20,
      "tense": {
        "major": "4",
        "minor": "11"
      }
    }
  },
  {
    "model": "verbs.tenses",
    "pk": 21,
    "fields": {
      "rank": 21,
      "tense": {
        "major": "4",
        "minor": "15"
      }
    }
  },
  {
    "model": "verbs.tenses",
    "pk": 22,
    "fields": {
      "rank": 22,
      "tense": {
        "major": "5",
        "minor": "11"
      }
    }
  },
  {
    "model": "verbs.tenses",
    "pk": 23,
    "fields": {
      "rank": 23,
      "tense": {
        "major": "5",
        "minor": "15"
      }
    }
  },
  {
    "model": "verbs.tenses",
    "pk": 24,
    "fields": {
      "rank": 24,
      "tense": {
        "major": "6",
        "minor": "11"
      }
    }
  },
  {
    "model": "verbs.tenses",
    "pk": 25,
    "fields": {
      "rank": 1,
      "tense": {
        "major": "7",
        "minor": "16"
      }
    }
  },
  {
    "model": "verbs.tenses",
    "pk": 26,
    "fields": {
      "rank": 2,
      "tense": {
        "major": "7",
        "minor": "17"
      }
    }
  },
  {
    "model": "verbs.tenses",
    "pk": 27,
    "fields": {
      "rank": 3,
      "tense": {
        "major": "7",
        "minor": "18"
      }
    }
  },
  {
    "model": "verbs.tenses",
    "pk": 28,
    "fields": {
      "rank": 4,
      "tense": {
        "major": "7",
        "minor": "19"
      }
    }
  },
  {
    "model": "verbs.tenses",
    "pk": 29,
    "fields": {
      "rank": 5,
      "tense": {
        "major": "7",
        "minor": "20"
      }
    }
  },
  {
    "model": "verbs.tenses",
    "pk": 30,
    "fields": {
      "rank": 6,
      "tense": {
        "major": "7",
        "minor": "21"
      }
    }
  },
  {
    "model": "verbs.tenses",
    "pk": 31,
    "fields": {
      "rank": 7,
      "tense": {
        "major": "7",
        "minor": "22"
      }
    }
  },
  {
    "model": "verbs.tenses",
    "pk": 32,
    "fields": {
      "rank": 8,
      "tense": {
        "major": "7",
        "minor": "23"
      }
    }
  },
  {
    "model": "verbs.tenses",
    "pk": 33,
    "fields": {
      "rank": 9,
      "tense": {
        "major": "7",
        "minor": "24"
      }
    }
  },
  {
    "model": "verbs.tenses",
    "pk": 34,
    "fields": {
      "rank": 10,
      "tense": {
        "major": "8",
        "minor": "16"
      }
    }
  },
  {
    "model": "verbs.tenses",
    "pk": 35,
    "fields": {
      "rank": 11,
      "tense": {
        "major": "8",
        "minor": "17"
      }
    }
  },
  {
    "model": "verbs.tenses",
    "pk": 36,
    "fields": {
      "rank": 12,
      "tense": {
        "major": "8",
        "minor": "18"
      }
    }
  },
  {
    "model": "verbs.tenses",
    "pk": 37,
    "fields": {
      "rank": 13,
      "tense": {
        "major": "8",
        "minor": "21"
      }
    }
  },
  {
    "model": "verbs.tenses",
    "pk": 38,
    "fields": {
      "rank": 14,
      "tense": {
        "major": "8",
        "minor": "25"
      }
    }
  },
  {
    "model": "verbs.tenses",
    "pk": 39,
    "fields": {
      "rank": 15,
      "tense": {
        "major": "8",
        "minor": "26"
      }
    }
  },
  {
    "model": "verbs.tenses",
    "pk": 40,
    "fields": {
      "rank": 16,
      "tense": {
        "major": "9",
        "minor": "27"
      }
    }
  },
  {
    "model": "verbs.tenses",
    "pk": 41,
    "fields": {
      "rank": 17,
      "tense": {
        "major": "9",
        "minor": "28"
      }
    }
  },
  {
    "model": "verbs.tenses",
    "pk": 42,
    "fields": {
      "rank": 18,
      "tense": {
        "major": "10",
        "minor": "29"
      }
    }
  },
  {
    "model": "verbs.tenses",
    "pk": 43,
    "fields": {
      "rank": 19,
      "tense": {
        "major": "11",
        "minor": "29"
      }
    }
  },
  {
    "model": "verbs.tenses",
    "pk": 44,
    "fields": {
      "rank": 20,
      "tense": {
        "major": "12",
        "minor": "29"
      }
    }
  },
  {
    "model": "verbs.tenses",
    "pk": 45,
    "fields": {
      "rank": 21,
      "tense": {
        "major": "12",
        "minor": "30"
      }
    }
  },
  {
    "model": "verbs.tenses",
    "pk": 46,
    "fields": {
      "rank": 22,
      "tense": {
        "major": "13",
        "minor": "29"
      }
    }
  },
  {
    "model": "verbs.tenses",
    "pk": 47,
    "fields": {
      "rank": 1,
      "tense": {
        "major": "14",
        "minor": "31"
      }
    }
  },
  {
    "model": "verbs.tenses",
    "pk": 48,
    "fields": {
      "rank": 2,
      "tense": {
        "major": "14",
        "minor": "32"
      }
    }
  },
  {
    "model": "verbs.tenses",
    "pk": 49,
    "fields": {
      "rank": 3,
      "tense": {
        "major": "14",
        "minor": "33"
      }
    }
  },
  {
    "model": "verbs.tenses",
    "pk": 50,
    "fields": {
      "rank": 4,
      "tense": {
        "major": "14",
        "minor": "34"
      }
    }
  },
  {
    "model": "verbs.tenses",
    "pk": 51,
    "fields": {
      "rank": 5,
      "tense": {
        "major": "14",
        "minor": "35"
      }
    }
  },
  {
    "model": "verbs.tenses",
    "pk": 52,
    "fields": {
      "rank": 6,
      "tense": {
        "major": "14",
        "minor": "36"
      }
    }
  },
  {
    "model": "verbs.tenses",
    "pk": 53,
    "fields": {
      "rank": 7,
      "tense": {
        "major": "14",
        "minor": "37"
      }
    }
  },
  {
    "model": "verbs.tenses",
    "pk": 54,
    "fields": {
      "rank": 8,
      "tense": {
        "major": "14",
        "minor": "38"
      }
    }
  },
  {
    "model": "verbs.tenses",
    "pk": 55,
    "fields": {
      "rank": 9,
      "tense": {
        "major": "15",
        "minor": "31"
      }
    }
  },
  {
    "model": "verbs.tenses",
    "pk": 56,
    "fields": {
      "rank": 10,
      "tense": {
        "major": "15",
        "minor": "39"
      }
    }
  },
  {
    "model": "verbs.tenses",
    "pk": 57,
    "fields": {
      "rank": 11,
      "tense": {
        "major": "15",
        "minor": "32"
      }
    }
  },
  {
    "model": "verbs.tenses",
    "pk": 58,
    "fields": {
      "rank": 12,
      "tense": {
        "major": "15",
        "minor": "40"
      }
    }
  },
  {
    "model": "verbs.tenses",
    "pk": 59,
    "fields": {
      "rank": 13,
      "tense": {
        "major": "16",
        "minor": "31"
      }
    }
  },
  {
    "model": "verbs.tenses",
    "pk": 60,
    "fields": {
      "rank": 14,
      "tense": {
        "major": "16",
        "minor": "39"
      }
    }
  },
  {
    "model": "verbs.tenses",
    "pk": 61,
    "fields": {
      "rank": 15,
      "tense": {
        "major": "17",
        "minor": "41"
      }
    }
  },
  {
    "model": "verbs.tenses",
    "pk": 62,
    "fields": {
      "rank": 16,
      "tense": {
        "major": "18",
        "minor": "31"
      }
    }
  },
  {
    "model": "verbs.tenses",
    "pk": 63,
    "fields": {
      "rank": 17,
      "tense": {
        "major": "18",
        "minor": "39"
      }
    }
  },
  {
    "model": "verbs.tenses",
    "pk": 64,
    "fields": {
      "rank": 18,
      "tense": {
        "major": "19",
        "minor": "41"
      }
    }
  },
  {
    "model": "verbs.tenses",
    "pk": 65,
    "fields": {
      "rank": 19,
      "tense": {
        "major": "20",
        "minor": "31"
      }
    }
  },
  {
    "model": "verbs.tenses",
    "pk": 66,
    "fields": {
      "rank": 20,
      "tense": {
        "major": "20",
        "minor": "39"
      }
    }
  },
  {
    "model": "verbs.tenses",
    "pk": 67,
    "fields": {
      "rank": 1,
      "tense": {
        "major": "21",
        "minor": "42"
      }
    }
  },
  {
    "model": "verbs.tenses",
    "pk": 68,
    "fields": {
      "rank": 2,
      "tense": {
        "major": "21",
        "minor": "43"
      }
    }
  },
  {
    "model": "verbs.tenses",
    "pk": 69,
    "fields": {
      "rank": 3,
      "tense": {
        "major": "21",
        "minor": "44"
      }
    }
  },
  {
    "model": "verbs.tenses",
    "pk": 70,
    "fields": {
      "rank": 4,
      "tense": {
        "major": "21",
        "minor": "45"
      }
    }
  },
  {
    "model": "verbs.tenses",
    "pk": 71,
    "fields": {
      "rank": 5,
      "tense": {
        "major": "21",
        "minor": "46"
      }
    }
  },
  {
    "model": "verbs.tenses",
    "pk": 72,
    "fields": {
      "rank": 6,
      "tense": {
        "major": "21",
        "minor": "47"
      }
    }
  },
  {
    "model": "verbs.tenses",
    "pk": 73,
    "fields": {
      "rank": 7,
      "tense": {
        "major": "21",
        "minor": "48"
      }
    }
  },
  {
    "model": "verbs.tenses",
    "pk": 74,
    "fields": {
      "rank": 8,
      "tense": {
        "major": "21",
        "minor": "49"
      }
    }
  },
  {
    "model": "verbs.tenses",
    "pk": 75,
    "fields": {
      "rank": 9,
      "tense": {
        "major": "22",
        "minor": "42"
      }
    }
  },
  {
    "model": "verbs.tenses",
    "pk": 76,
    "fields": {
      "rank": 10,
      "tense": {
        "major": "22",
        "minor": "43"
      }
    }
  },
  {
    "model": "verbs.tenses",
    "pk": 77,
    "fields": {
      "rank": 11,
      "tense": {
        "major": "22",
        "minor": "47"
      }
    }
  },
  {
    "model": "verbs.tenses",
    "pk": 78,
    "fields": {
      "rank": 12,
      "tense": {
        "major": "22",
        "minor": "50"
      }
    }
  },
  {
    "model": "verbs.tenses",
    "pk": 79,
    "fields": {
      "rank": 13,
      "tense": {
        "major": "23",
        "minor": "42"
      }
    }
  },
  {
    "model": "verbs.tenses",
    "pk": 80,
    "fields": {
      "rank": 14,
      "tense": {
        "major": "23",
        "minor": "51"
      }
    }
  },
  {
    "model": "verbs.tenses",
    "pk": 81,
    "fields": {
      "rank": 15,
      "tense": {
        "major": "23",
        "minor": "52"
      }
    }
  },
  {
    "model": "verbs.tenses",
    "pk": 82,
    "fields": {
      "rank": 16,
      "tense": {
        "major": "24",
        "minor": "42"
      }
    }
  },
  {
    "model": "verbs.tenses",
    "pk": 83,
    "fields": {
      "rank": 17,
      "tense": {
        "major": "24",
        "minor": "46"
      }
    }
  },
  {
    "model": "verbs.tenses",
    "pk": 84,
    "fields": {
      "rank": 18,
      "tense": {
        "major": "24",
        "minor": "50"
      }
    }
  },
  {
    "model": "verbs.tenses",
    "pk": 85,
    "fields": {
      "rank": 19,
      "tense": {
        "major": "25",
        "minor": "42"
      }
    }
  },
  {
    "model": "verbs.tenses",
    "pk": 86,
    "fields": {
      "rank": 20,
      "tense": {
        "major": "25",
        "minor": "50"
      }
    }
  },
  {
    "model": "verbs.tenses",
    "pk": 87,
    "fields": {
      "rank": 21,
      "tense": {
        "major": "26",
        "minor": "42"
      }
    }
  },
  {
    "model": "verbs.tenses",
    "pk": 88,
    "fields": {
      "rank": 22,
      "tense": {
        "major": "26",
        "minor": "50"
      }
    }
  },
  {
    "model": "verbs.tenses",
    "pk": 89,
    "fields": {
      "rank": 19,
      "tense": {
        "major": "27",
        "minor": "53"
      }
    }
  },
  {
    "model": "verbs.tenses",
    "pk": 90,
    "fields": {
      "rank": 1,
      "tense": {
        "major": "28",
        "minor": "54"
      }
    }
  },
  {
    "model": "verbs.tenses",
    "pk": 91,
    "fields": {
      "rank": 2,
      "tense": {
        "major": "28",
        "minor": "55"
      }
    }
  },
  {
    "model": "verbs.tenses",
    "pk": 92,
    "fields": {
      "rank": 3,
      "tense": {
        "major": "28",
        "minor": "56"
      }
    }
  },
  {
    "model": "verbs.tenses",
    "pk": 93,
    "fields": {
      "rank": 4,
      "tense": {
        "major": "28",
        "minor": "57"
      }
    }
  },
  {
    "model": "verbs.tenses",
    "pk": 94,
    "fields": {
      "rank": 5,
      "tense": {
        "major": "28",
        "minor": "58"
      }
    }
  },
  {
    "model": "verbs.tenses",
    "pk": 95,
    "fields": {
      "rank": 6,
      "tense": {
        "major": "28",
        "minor": "59"
      }
    }
  },
  {
    "model": "verbs.tenses",
    "pk": 96,
    "fields": {
      "rank": 7,
      "tense": {
        "major": "28",
        "minor": "60"
      }
    }
  },
  {
    "model": "verbs.tenses",
    "pk": 97,
    "fields": {
      "rank": 8,
      "tense": {
        "major": "28",
        "minor": "61"
      }
    }
  },
  {
    "model": "verbs.tenses",
    "pk": 98,
    "fields": {
      "rank": 9,
      "tense": {
        "major": "28",
        "minor": "62"
      }
    }
  },
  {
    "model": "verbs.tenses",
    "pk": 99,
    "fields": {
      "rank": 10,
      "tense": {
        "major": "28",
        "minor": "63"
      }
    }
  },
  {
    "model": "verbs.tenses",
    "pk": 100,
    "fields": {
      "rank": 11,
      "tense": {
        "major": "28",
        "minor": "64"
      }
    }
  },
  {
    "model": "verbs.tenses",
    "pk": 101,
    "fields": {
      "rank": 12,
      "tense": {
        "major": "28",
        "minor": "65"
      }
    }
  },
  {
    "model": "verbs.tenses",
    "pk": 102,
    "fields": {
      "rank": 13,
      "tense": {
        "major": "29",
        "minor": "66"
      }
    }
  },
  {
    "model": "verbs.tenses",
    "pk": 103,
    "fields": {
      "rank": 14,
      "tense": {
        "major": "30",
        "minor": "54"
      }
    }
  },
  {
    "model": "verbs.tenses",
    "pk": 104,
    "fields": {
      "rank": 15,
      "tense": {
        "major": "30",
        "minor": "67"
      }
    }
  },
  {
    "model": "verbs.tenses",
    "pk": 105,
    "fields": {
      "rank": 16,
      "tense": {
        "major": "31",
        "minor": "66"
      }
    }
  },
  {
    "model": "verbs.tenses",
    "pk": 106,
    "fields": {
      "rank": 17,
      "tense": {
        "major": "32",
        "minor": "66"
      }
    }
  }
]